flashtest/__init__.py
flashtest/ai_exploit.py
flashtest/cli.py
flashtest/recon.py
flashtest/scanner.py
flashtest-0.1.5.dist-info/LICENSE
flashtest-0.1.5.dist-info/METADATA
flashtest-0.1.5.dist-info/WHEEL
flashtest-0.1.5.dist-info/entry_points.txt
flashtest-0.1.5.dist-info/top_level.txt
flashtest-0.1.5.dist-info/RECORD
