Metadata-Version: 2.2
Name: flashtest
Version: 0.1.5
Summary: A CLI-based penetration testing tool with reconnaissance and AI-driven exploits.
Home-page: https://github.com/shubham-parida01/flashtest
Author: Shubham Parida
Author-email: paridashub9871@gmail.com
Classifier: Programming Language :: Python :: 3
Classifier: License :: OSI Approved :: MIT License
Classifier: Operating System :: OS Independent
Requires-Python: >=3.6
License-File: LICENSE
Requires-Dist: requests
Requires-Dist: whois
Dynamic: author
Dynamic: author-email
Dynamic: classifier
Dynamic: description
Dynamic: description-content-type
Dynamic: home-page
Dynamic: requires-dist
Dynamic: requires-python
Dynamic: summary
